[
  {
    "name": "101mazes.png",
    "href": "101mazes.png",
    "url": "https://myrient.erista.me/files/MAME/EXTRAs/all_non-zipped_content/snap_SL/ibm5150/101mazes.png",
    "is_dir": false,
    "size": "4.0 KiB",
    "date": "28-Sep-2025 13:24"
  },
  {
    "name": "1on1.png",
    "href": "1on1.png",
    "url": "https://myrient.erista.me/files/MAME/EXTRAs/all_non-zipped_content/snap_SL/ibm5150/1on1.png",
    "is_dir": false,
    "size": "2.0 KiB",
    "date": "28-Sep-2025 13:24"
  },
  {
    "name": "2400ad.png",
    "href": "2400ad.png",
    "url": "https://myrient.erista.me/files/MAME/EXTRAs/all_non-zipped_content/snap_SL/ibm5150/2400ad.png",
    "is_dir": false,
    "size": "3.3 KiB",
    "date": "28-Sep-2025 13:24"
  },
  {
    "name": "2400ad1.png",
    "href": "2400ad1.png",
    "url": "https://myrient.erista.me/files/MAME/EXTRAs/all_non-zipped_content/snap_SL/ibm5150/2400ad1.png",
    "is_dir": false,
    "size": "4.4 KiB",
    "date": "28-Sep-2025 13:24"
  },
  {
    "name": "3ktrivia.png",
    "href": "3ktrivia.png",
    "url": "https://myrient.erista.me/files/MAME/EXTRAs/all_non-zipped_content/snap_SL/ibm5150/3ktrivia.png",
    "is_dir": false,
    "size": "2.4 KiB",
    "date": "28-Sep-2025 13:24"
  },
  {
    "name": "4dboxing.png",
    "href": "4dboxing.png",
    "url": "https://myrient.erista.me/files/MAME/EXTRAs/all_non-zipped_content/snap_SL/ibm5150/4dboxing.png",
    "is_dir": false,
    "size": "21.6 KiB",
    "date": "28-Sep-2025 13:24"
  },
  {
    "name": "4dsboxin.png",
    "href": "4dsboxin.png",
    "url": "https://myrient.erista.me/files/MAME/EXTRAs/all_non-zipped_content/snap_SL/ibm5150/4dsboxin.png",
    "is_dir": false,
    "size": "21.3 KiB",
    "date": "28-Sep-2025 13:24"
  },
  {
    "name": "4ptgraph.png",
    "href": "4ptgraph.png",
    "url": "https://myrient.erista.me/files/MAME/EXTRAs/all_non-zipped_content/snap_SL/ibm5150/4ptgraph.png",
    "is_dir": false,
    "size": "2.8 KiB",
    "date": "28-Sep-2025 13:24"
  },
  {
    "name": "4thprot.png",
    "href": "4thprot.png",
    "url": "https://myrient.erista.me/files/MAME/EXTRAs/all_non-zipped_content/snap_SL/ibm5150/4thprot.png",
    "is_dir": false,
    "size": "4.1 KiB",
    "date": "28-Sep-2025 13:24"
  },
  {
    "name": "5soccer.png",
    "href": "5soccer.png",
    "url": "https://myrient.erista.me/files/MAME/EXTRAs/all_non-zipped_content/snap_SL/ibm5150/5soccer.png",
    "is_dir": false,
    "size": "3.3 KiB",
    "date": "28-Sep-2025 13:24"
  },
  {
    "name": "688atsub.png",
    "href": "688atsub.png",
    "url": "https://myrient.erista.me/files/MAME/EXTRAs/all_non-zipped_content/snap_SL/ibm5150/688atsub.png",
    "is_dir": false,
    "size": "11.0 KiB",
    "date": "28-Sep-2025 13:24"
  },
  {
    "name": "7citygld.png",
    "href": "7citygld.png",
    "url": "https://myrient.erista.me/files/MAME/EXTRAs/all_non-zipped_content/snap_SL/ibm5150/7citygld.png",
    "is_dir": false,
    "size": "24.2 KiB",
    "date": "28-Sep-2025 13:24"
  },
  {
    "name": "8088mph.png",
    "href": "8088mph.png",
    "url": "https://myrient.erista.me/files/MAME/EXTRAs/all_non-zipped_content/snap_SL/ibm5150/8088mph.png",
    "is_dir": false,
    "size": "4.1 KiB",
    "date": "28-Sep-2025 13:24"
  },
  {
    "name": "8088mphp.png",
    "href": "8088mphp.png",
    "url": "https://myrient.erista.me/files/MAME/EXTRAs/all_non-zipped_content/snap_SL/ibm5150/8088mphp.png",
    "is_dir": false,
    "size": "12.3 KiB",
    "date": "28-Sep-2025 13:24"
  },
  {
    "name": "a10tank.png",
    "href": "a10tank.png",
    "url": "https://myrient.erista.me/files/MAME/EXTRAs/all_non-zipped_content/snap_SL/ibm5150/a10tank.png",
    "is_dir": false,
    "size": "26.7 KiB",
    "date": "28-Sep-2025 13:24"
  },
  {
    "name": "aaow.png",
    "href": "aaow.png",
    "url": "https://myrient.erista.me/files/MAME/EXTRAs/all_non-zipped_content/snap_SL/ibm5150/aaow.png",
    "is_dir": false,
    "size": "3.7 KiB",
    "date": "28-Sep-2025 13:24"
  },
  {
    "name": "aaowas.png",
    "href": "aaowas.png",
    "url": "https://myrient.erista.me/files/MAME/EXTRAs/all_non-zipped_content/snap_SL/ibm5150/aaowas.png",
    "is_dir": false,
    "size": "1.2 KiB",
    "date": "28-Sep-2025 13:24"
  },
  {
    "name": "aaowasa.png",
    "href": "aaowasa.png",
    "url": "https://myrient.erista.me/files/MAME/EXTRAs/all_non-zipped_content/snap_SL/ibm5150/aaowasa.png",
    "is_dir": false,
    "size": "1.2 KiB",
    "date": "28-Sep-2025 13:24"
  },
  {
    "name": "abcbox.png",
    "href": "abcbox.png",
    "url": "https://myrient.erista.me/files/MAME/EXTRAs/all_non-zipped_content/snap_SL/ibm5150/abcbox.png",
    "is_dir": false,
    "size": "8.1 KiB",
    "date": "28-Sep-2025 13:24"
  },
  {
    "name": "abilityd.png",
    "href": "abilityd.png",
    "url": "https://myrient.erista.me/files/MAME/EXTRAs/all_non-zipped_content/snap_SL/ibm5150/abilityd.png",
    "is_dir": false,
    "size": "1.2 KiB",
    "date": "28-Sep-2025 13:24"
  },
  {
    "name": "academy.png",
    "href": "academy.png",
    "url": "https://myrient.erista.me/files/MAME/EXTRAs/all_non-zipped_content/snap_SL/ibm5150/academy.png",
    "is_dir": false,
    "size": "10.1 KiB",
    "date": "28-Sep-2025 13:24"
  },
  {
    "name": "aceoface.png",
    "href": "aceoface.png",
    "url": "https://myrient.erista.me/files/MAME/EXTRAs/all_non-zipped_content/snap_SL/ibm5150/aceoface.png",
    "is_dir": false,
    "size": "11.7 KiB",
    "date": "28-Sep-2025 13:24"
  },
  {
    "name": "aceshigh.png",
    "href": "aceshigh.png",
    "url": "https://myrient.erista.me/files/MAME/EXTRAs/all_non-zipped_content/snap_SL/ibm5150/aceshigh.png",
    "is_dir": false,
    "size": "2.5 KiB",
    "date": "28-Sep-2025 13:24"
  },
  {
    "name": "actionfg.png",
    "href": "actionfg.png",
    "url": "https://myrient.erista.me/files/MAME/EXTRAs/all_non-zipped_content/snap_SL/ibm5150/actionfg.png",
    "is_dir": false,
    "size": "3.6 KiB",
    "date": "28-Sep-2025 13:24"
  },
  {
    "name": "actnserv.png",
    "href": "actnserv.png",
    "url": "https://myrient.erista.me/files/MAME/EXTRAs/all_non-zipped_content/snap_SL/ibm5150/actnserv.png",
    "is_dir": false,
    "size": "6.9 KiB",
    "date": "28-Sep-2025 13:24"
  },
  {
    "name": "advmath.png",
    "href": "advmath.png",
    "url": "https://myrient.erista.me/files/MAME/EXTRAs/all_non-zipped_content/snap_SL/ibm5150/advmath.png",
    "is_dir": false,
    "size": "3.5 KiB",
    "date": "28-Sep-2025 13:24"
  },
  {
    "name": "agentusa.png",
    "href": "agentusa.png",
    "url": "https://myrient.erista.me/files/MAME/EXTRAs/all_non-zipped_content/snap_SL/ibm5150/agentusa.png",
    "is_dir": false,
    "size": "2.9 KiB",
    "date": "28-Sep-2025 13:24"
  },
  {
    "name": "airbrang.png",
    "href": "airbrang.png",
    "url": "https://myrient.erista.me/files/MAME/EXTRAs/all_non-zipped_content/snap_SL/ibm5150/airbrang.png",
    "is_dir": false,
    "size": "6.8 KiB",
    "date": "28-Sep-2025 13:24"
  },
  {
    "name": "alf.png",
    "href": "alf.png",
    "url": "https://myrient.erista.me/files/MAME/EXTRAs/all_non-zipped_content/snap_SL/ibm5150/alf.png",
    "is_dir": false,
    "size": "3.9 KiB",
    "date": "28-Sep-2025 13:24"
  },
  {
    "name": "alleycat.png",
    "href": "alleycat.png",
    "url": "https://myrient.erista.me/files/MAME/EXTRAs/all_non-zipped_content/snap_SL/ibm5150/alleycat.png",
    "is_dir": false,
    "size": "4.9 KiB",
    "date": "28-Sep-2025 13:24"
  },
  {
    "name": "alpine.png",
    "href": "alpine.png",
    "url": "https://myrient.erista.me/files/MAME/EXTRAs/all_non-zipped_content/snap_SL/ibm5150/alpine.png",
    "is_dir": false,
    "size": "5.5 KiB",
    "date": "28-Sep-2025 13:24"
  },
  {
    "name": "alpntram.png",
    "href": "alpntram.png",
    "url": "https://myrient.erista.me/files/MAME/EXTRAs/all_non-zipped_content/snap_SL/ibm5150/alpntram.png",
    "is_dir": false,
    "size": "5.6 KiB",
    "date": "28-Sep-2025 13:24"
  },
  {
    "name": "amnesia.png",
    "href": "amnesia.png",
    "url": "https://myrient.erista.me/files/MAME/EXTRAs/all_non-zipped_content/snap_SL/ibm5150/amnesia.png",
    "is_dir": false,
    "size": "4.8 KiB",
    "date": "28-Sep-2025 13:24"
  },
  {
    "name": "aplepanc.png",
    "href": "aplepanc.png",
    "url": "https://myrient.erista.me/files/MAME/EXTRAs/all_non-zipped_content/snap_SL/ibm5150/aplepanc.png",
    "is_dir": false,
    "size": "2.4 KiB",
    "date": "28-Sep-2025 13:24"
  },
  {
    "name": "arcadefb.png",
    "href": "arcadefb.png",
    "url": "https://myrient.erista.me/files/MAME/EXTRAs/all_non-zipped_content/snap_SL/ibm5150/arcadefb.png",
    "is_dir": false,
    "size": "1.2 KiB",
    "date": "28-Sep-2025 13:24"
  },
  {
    "name": "archon.png",
    "href": "archon.png",
    "url": "https://myrient.erista.me/files/MAME/EXTRAs/all_non-zipped_content/snap_SL/ibm5150/archon.png",
    "is_dir": false,
    "size": "335 B",
    "date": "28-Sep-2025 13:24"
  },
  {
    "name": "archon1.png",
    "href": "archon1.png",
    "url": "https://myrient.erista.me/files/MAME/EXTRAs/all_non-zipped_content/snap_SL/ibm5150/archon1.png",
    "is_dir": false,
    "size": "336 B",
    "date": "28-Sep-2025 13:24"
  },
  {
    "name": "arctadv.png",
    "href": "arctadv.png",
    "url": "https://myrient.erista.me/files/MAME/EXTRAs/all_non-zipped_content/snap_SL/ibm5150/arctadv.png",
    "is_dir": false,
    "size": "7.5 KiB",
    "date": "28-Sep-2025 13:24"
  },
  {
    "name": "arknoid2.png",
    "href": "arknoid2.png",
    "url": "https://myrient.erista.me/files/MAME/EXTRAs/all_non-zipped_content/snap_SL/ibm5150/arknoid2.png",
    "is_dir": false,
    "size": "21.7 KiB",
    "date": "28-Sep-2025 13:24"
  },
  {
    "name": "arknoid2a.png",
    "href": "arknoid2a.png",
    "url": "https://myrient.erista.me/files/MAME/EXTRAs/all_non-zipped_content/snap_SL/ibm5150/arknoid2a.png",
    "is_dir": false,
    "size": "1.2 KiB",
    "date": "28-Sep-2025 13:24"
  },
  {
    "name": "armorik.png",
    "href": "armorik.png",
    "url": "https://myrient.erista.me/files/MAME/EXTRAs/all_non-zipped_content/snap_SL/ibm5150/armorik.png",
    "is_dir": false,
    "size": "1.3 KiB",
    "date": "28-Sep-2025 13:24"
  },
  {
    "name": "astrodod.png",
    "href": "astrodod.png",
    "url": "https://myrient.erista.me/files/MAME/EXTRAs/all_non-zipped_content/snap_SL/ibm5150/astrodod.png",
    "is_dir": false,
    "size": "629 B",
    "date": "28-Sep-2025 13:24"
  },
  {
    "name": "atrain.png",
    "href": "atrain.png",
    "url": "https://myrient.erista.me/files/MAME/EXTRAs/all_non-zipped_content/snap_SL/ibm5150/atrain.png",
    "is_dir": false,
    "size": "28.6 KiB",
    "date": "28-Sep-2025 13:24"
  },
  {
    "name": "azurebnd.png",
    "href": "azurebnd.png",
    "url": "https://myrient.erista.me/files/MAME/EXTRAs/all_non-zipped_content/snap_SL/ibm5150/azurebnd.png",
    "is_dir": false,
    "size": "14.4 KiB",
    "date": "28-Sep-2025 13:24"
  },
  {
    "name": "azurebnda.png",
    "href": "azurebnda.png",
    "url": "https://myrient.erista.me/files/MAME/EXTRAs/all_non-zipped_content/snap_SL/ibm5150/azurebnda.png",
    "is_dir": false,
    "size": "14.3 KiB",
    "date": "28-Sep-2025 13:24"
  },
  {
    "name": "babyjo.png",
    "href": "babyjo.png",
    "url": "https://myrient.erista.me/files/MAME/EXTRAs/all_non-zipped_content/snap_SL/ibm5150/babyjo.png",
    "is_dir": false,
    "size": "6.7 KiB",
    "date": "28-Sep-2025 13:24"
  },
  {
    "name": "backgamm.png",
    "href": "backgamm.png",
    "url": "https://myrient.erista.me/files/MAME/EXTRAs/all_non-zipped_content/snap_SL/ibm5150/backgamm.png",
    "is_dir": false,
    "size": "4.9 KiB",
    "date": "28-Sep-2025 13:24"
  },
  {
    "name": "baddudes.png",
    "href": "baddudes.png",
    "url": "https://myrient.erista.me/files/MAME/EXTRAs/all_non-zipped_content/snap_SL/ibm5150/baddudes.png",
    "is_dir": false,
    "size": "3.3 KiB",
    "date": "28-Sep-2025 13:24"
  },
  {
    "name": "bargames.png",
    "href": "bargames.png",
    "url": "https://myrient.erista.me/files/MAME/EXTRAs/all_non-zipped_content/snap_SL/ibm5150/bargames.png",
    "is_dir": false,
    "size": "7.5 KiB",
    "date": "28-Sep-2025 13:24"
  },
  {
    "name": "bartvssm.png",
    "href": "bartvssm.png",
    "url": "https://myrient.erista.me/files/MAME/EXTRAs/all_non-zipped_content/snap_SL/ibm5150/bartvssm.png",
    "is_dir": false,
    "size": "5.0 KiB",
    "date": "28-Sep-2025 13:24"
  },
  {
    "name": "baseball.png",
    "href": "baseball.png",
    "url": "https://myrient.erista.me/files/MAME/EXTRAs/all_non-zipped_content/snap_SL/ibm5150/baseball.png",
    "is_dir": false,
    "size": "103.8 KiB",
    "date": "28-Sep-2025 13:24"
  },
  {
    "name": "bat.png",
    "href": "bat.png",
    "url": "https://myrient.erista.me/files/MAME/EXTRAs/all_non-zipped_content/snap_SL/ibm5150/bat.png",
    "is_dir": false,
    "size": "12.0 KiB",
    "date": "28-Sep-2025 13:24"
  },
  {
    "name": "batmanmv.png",
    "href": "batmanmv.png",
    "url": "https://myrient.erista.me/files/MAME/EXTRAs/all_non-zipped_content/snap_SL/ibm5150/batmanmv.png",
    "is_dir": false,
    "size": "5.4 KiB",
    "date": "28-Sep-2025 13:24"
  },
  {
    "name": "bcquest.png",
    "href": "bcquest.png",
    "url": "https://myrient.erista.me/files/MAME/EXTRAs/all_non-zipped_content/snap_SL/ibm5150/bcquest.png",
    "is_dir": false,
    "size": "2.2 KiB",
    "date": "28-Sep-2025 13:24"
  },
  {
    "name": "bcwolfen.png",
    "href": "bcwolfen.png",
    "url": "https://myrient.erista.me/files/MAME/EXTRAs/all_non-zipped_content/snap_SL/ibm5150/bcwolfen.png",
    "is_dir": false,
    "size": "1.8 KiB",
    "date": "28-Sep-2025 13:24"
  },
  {
    "name": "bdash.png",
    "href": "bdash.png",
    "url": "https://myrient.erista.me/files/MAME/EXTRAs/all_non-zipped_content/snap_SL/ibm5150/bdash.png",
    "is_dir": false,
    "size": "3.3 KiB",
    "date": "28-Sep-2025 13:24"
  },
  {
    "name": "bdashkit.png",
    "href": "bdashkit.png",
    "url": "https://myrient.erista.me/files/MAME/EXTRAs/all_non-zipped_content/snap_SL/ibm5150/bdashkit.png",
    "is_dir": false,
    "size": "5.1 KiB",
    "date": "28-Sep-2025 13:24"
  },
  {
    "name": "belowrot.png",
    "href": "belowrot.png",
    "url": "https://myrient.erista.me/files/MAME/EXTRAs/all_non-zipped_content/snap_SL/ibm5150/belowrot.png",
    "is_dir": false,
    "size": "4.3 KiB",
    "date": "28-Sep-2025 13:24"
  },
  {
    "name": "bigtop.png",
    "href": "bigtop.png",
    "url": "https://myrient.erista.me/files/MAME/EXTRAs/all_non-zipped_content/snap_SL/ibm5150/bigtop.png",
    "is_dir": false,
    "size": "2.7 KiB",
    "date": "28-Sep-2025 13:24"
  },
  {
    "name": "breach2.png",
    "href": "breach2.png",
    "url": "https://myrient.erista.me/files/MAME/EXTRAs/all_non-zipped_content/snap_SL/ibm5150/breach2.png",
    "is_dir": false,
    "size": "4.5 KiB",
    "date": "28-Sep-2025 13:24"
  },
  {
    "name": "brucelee.png",
    "href": "brucelee.png",
    "url": "https://myrient.erista.me/files/MAME/EXTRAs/all_non-zipped_content/snap_SL/ibm5150/brucelee.png",
    "is_dir": false,
    "size": "1.7 KiB",
    "date": "28-Sep-2025 13:24"
  },
  {
    "name": "btlchess.png",
    "href": "btlchess.png",
    "url": "https://myrient.erista.me/files/MAME/EXTRAs/all_non-zipped_content/snap_SL/ibm5150/btlchess.png",
    "is_dir": false,
    "size": "33.0 KiB",
    "date": "28-Sep-2025 13:24"
  },
  {
    "name": "bttf2.png",
    "href": "bttf2.png",
    "url": "https://myrient.erista.me/files/MAME/EXTRAs/all_non-zipped_content/snap_SL/ibm5150/bttf2.png",
    "is_dir": false,
    "size": "15.0 KiB",
    "date": "28-Sep-2025 13:24"
  },
  {
    "name": "bublbobl.png",
    "href": "bublbobl.png",
    "url": "https://myrient.erista.me/files/MAME/EXTRAs/all_non-zipped_content/snap_SL/ibm5150/bublbobl.png",
    "is_dir": false,
    "size": "15.4 KiB",
    "date": "28-Sep-2025 13:24"
  },
  {
    "name": "buckrog.png",
    "href": "buckrog.png",
    "url": "https://myrient.erista.me/files/MAME/EXTRAs/all_non-zipped_content/snap_SL/ibm5150/buckrog.png",
    "is_dir": false,
    "size": "1.0 KiB",
    "date": "28-Sep-2025 13:24"
  },
  {
    "name": "budokan.png",
    "href": "budokan.png",
    "url": "https://myrient.erista.me/files/MAME/EXTRAs/all_non-zipped_content/snap_SL/ibm5150/budokan.png",
    "is_dir": false,
    "size": "25.5 KiB",
    "date": "28-Sep-2025 13:24"
  },
  {
    "name": "bugrangr.png",
    "href": "bugrangr.png",
    "url": "https://myrient.erista.me/files/MAME/EXTRAs/all_non-zipped_content/snap_SL/ibm5150/bugrangr.png",
    "is_dir": false,
    "size": "7.4 KiB",
    "date": "28-Sep-2025 13:24"
  },
  {
    "name": "burgtime.png",
    "href": "burgtime.png",
    "url": "https://myrient.erista.me/files/MAME/EXTRAs/all_non-zipped_content/snap_SL/ibm5150/burgtime.png",
    "is_dir": false,
    "size": "1.7 KiB",
    "date": "28-Sep-2025 13:24"
  },
  {
    "name": "bzone.png",
    "href": "bzone.png",
    "url": "https://myrient.erista.me/files/MAME/EXTRAs/all_non-zipped_content/snap_SL/ibm5150/bzone.png",
    "is_dir": false,
    "size": "2.5 KiB",
    "date": "28-Sep-2025 13:24"
  },
  {
    "name": "cadaver.png",
    "href": "cadaver.png",
    "url": "https://myrient.erista.me/files/MAME/EXTRAs/all_non-zipped_content/snap_SL/ibm5150/cadaver.png",
    "is_dir": false,
    "size": "11.9 KiB",
    "date": "28-Sep-2025 13:24"
  },
  {
    "name": "capblood.png",
    "href": "capblood.png",
    "url": "https://myrient.erista.me/files/MAME/EXTRAs/all_non-zipped_content/snap_SL/ibm5150/capblood.png",
    "is_dir": false,
    "size": "7.3 KiB",
    "date": "28-Sep-2025 13:24"
  },
  {
    "name": "captcom.png",
    "href": "captcom.png",
    "url": "https://myrient.erista.me/files/MAME/EXTRAs/all_non-zipped_content/snap_SL/ibm5150/captcom.png",
    "is_dir": false,
    "size": "3.0 KiB",
    "date": "28-Sep-2025 13:24"
  },
  {
    "name": "caveugh.png",
    "href": "caveugh.png",
    "url": "https://myrient.erista.me/files/MAME/EXTRAs/all_non-zipped_content/snap_SL/ibm5150/caveugh.png",
    "is_dir": false,
    "size": "12.5 KiB",
    "date": "28-Sep-2025 13:24"
  },
  {
    "name": "cboxing.png",
    "href": "cboxing.png",
    "url": "https://myrient.erista.me/files/MAME/EXTRAs/all_non-zipped_content/snap_SL/ibm5150/cboxing.png",
    "is_dir": false,
    "size": "3.1 KiB",
    "date": "28-Sep-2025 13:24"
  },
  {
    "name": "centiped.png",
    "href": "centiped.png",
    "url": "https://myrient.erista.me/files/MAME/EXTRAs/all_non-zipped_content/snap_SL/ibm5150/centiped.png",
    "is_dir": false,
    "size": "697 B",
    "date": "28-Sep-2025 13:24"
  },
  {
    "name": "chipdale.png",
    "href": "chipdale.png",
    "url": "https://myrient.erista.me/files/MAME/EXTRAs/all_non-zipped_content/snap_SL/ibm5150/chipdale.png",
    "is_dir": false,
    "size": "28.2 KiB",
    "date": "28-Sep-2025 13:24"
  },
  {
    "name": "cloderun.png",
    "href": "cloderun.png",
    "url": "https://myrient.erista.me/files/MAME/EXTRAs/all_non-zipped_content/snap_SL/ibm5150/cloderun.png",
    "is_dir": false,
    "size": "2.6 KiB",
    "date": "28-Sep-2025 13:24"
  },
  {
    "name": "commando.png",
    "href": "commando.png",
    "url": "https://myrient.erista.me/files/MAME/EXTRAs/all_non-zipped_content/snap_SL/ibm5150/commando.png",
    "is_dir": false,
    "size": "2.6 KiB",
    "date": "28-Sep-2025 13:24"
  },
  {
    "name": "condos32.png",
    "href": "condos32.png",
    "url": "https://myrient.erista.me/files/MAME/EXTRAs/all_non-zipped_content/snap_SL/ibm5150/condos32.png",
    "is_dir": false,
    "size": "2.8 KiB",
    "date": "28-Sep-2025 13:24"
  },
  {
    "name": "congo.png",
    "href": "congo.png",
    "url": "https://myrient.erista.me/files/MAME/EXTRAs/all_non-zipped_content/snap_SL/ibm5150/congo.png",
    "is_dir": false,
    "size": "5.2 KiB",
    "date": "28-Sep-2025 13:24"
  },
  {
    "name": "cpm8610.png",
    "href": "cpm8610.png",
    "url": "https://myrient.erista.me/files/MAME/EXTRAs/all_non-zipped_content/snap_SL/ibm5150/cpm8610.png",
    "is_dir": false,
    "size": "8.2 KiB",
    "date": "28-Sep-2025 13:24"
  },
  {
    "name": "cpm8611.png",
    "href": "cpm8611.png",
    "url": "https://myrient.erista.me/files/MAME/EXTRAs/all_non-zipped_content/snap_SL/ibm5150/cpm8611.png",
    "is_dir": false,
    "size": "1.2 KiB",
    "date": "28-Sep-2025 13:24"
  },
  {
    "name": "crimewav.png",
    "href": "crimewav.png",
    "url": "https://myrient.erista.me/files/MAME/EXTRAs/all_non-zipped_content/snap_SL/ibm5150/crimewav.png",
    "is_dir": false,
    "size": "39.7 KiB",
    "date": "28-Sep-2025 13:24"
  },
  {
    "name": "ddragon.png",
    "href": "ddragon.png",
    "url": "https://myrient.erista.me/files/MAME/EXTRAs/all_non-zipped_content/snap_SL/ibm5150/ddragon.png",
    "is_dir": false,
    "size": "19.8 KiB",
    "date": "28-Sep-2025 13:24"
  },
  {
    "name": "ddragon2.png",
    "href": "ddragon2.png",
    "url": "https://myrient.erista.me/files/MAME/EXTRAs/all_non-zipped_content/snap_SL/ibm5150/ddragon2.png",
    "is_dir": false,
    "size": "17.9 KiB",
    "date": "28-Sep-2025 13:24"
  },
  {
    "name": "ddragon3.png",
    "href": "ddragon3.png",
    "url": "https://myrient.erista.me/files/MAME/EXTRAs/all_non-zipped_content/snap_SL/ibm5150/ddragon3.png",
    "is_dir": false,
    "size": "36.4 KiB",
    "date": "28-Sep-2025 13:24"
  },
  {
    "name": "defcrown.png",
    "href": "defcrown.png",
    "url": "https://myrient.erista.me/files/MAME/EXTRAs/all_non-zipped_content/snap_SL/ibm5150/defcrown.png",
    "is_dir": false,
    "size": "7.0 KiB",
    "date": "28-Sep-2025 13:24"
  },
  {
    "name": "defender.png",
    "href": "defender.png",
    "url": "https://myrient.erista.me/files/MAME/EXTRAs/all_non-zipped_content/snap_SL/ibm5150/defender.png",
    "is_dir": false,
    "size": "1.3 KiB",
    "date": "28-Sep-2025 13:24"
  },
  {
    "name": "diehard.png",
    "href": "diehard.png",
    "url": "https://myrient.erista.me/files/MAME/EXTRAs/all_non-zipped_content/snap_SL/ibm5150/diehard.png",
    "is_dir": false,
    "size": "8.5 KiB",
    "date": "28-Sep-2025 13:24"
  },
  {
    "name": "digger.png",
    "href": "digger.png",
    "url": "https://myrient.erista.me/files/MAME/EXTRAs/all_non-zipped_content/snap_SL/ibm5150/digger.png",
    "is_dir": false,
    "size": "4.1 KiB",
    "date": "28-Sep-2025 13:24"
  },
  {
    "name": "donald.png",
    "href": "donald.png",
    "url": "https://myrient.erista.me/files/MAME/EXTRAs/all_non-zipped_content/snap_SL/ibm5150/donald.png",
    "is_dir": false,
    "size": "2.1 KiB",
    "date": "28-Sep-2025 13:24"
  },
  {
    "name": "ferrarf1.png",
    "href": "ferrarf1.png",
    "url": "https://myrient.erista.me/files/MAME/EXTRAs/all_non-zipped_content/snap_SL/ibm5150/ferrarf1.png",
    "is_dir": false,
    "size": "17.4 KiB",
    "date": "28-Sep-2025 13:24"
  },
  {
    "name": "fpcarcad.png",
    "href": "fpcarcad.png",
    "url": "https://myrient.erista.me/files/MAME/EXTRAs/all_non-zipped_content/snap_SL/ibm5150/fpcarcad.png",
    "is_dir": false,
    "size": "3.5 KiB",
    "date": "28-Sep-2025 13:24"
  },
  {
    "name": "fredhard.png",
    "href": "fredhard.png",
    "url": "https://myrient.erista.me/files/MAME/EXTRAs/all_non-zipped_content/snap_SL/ibm5150/fredhard.png",
    "is_dir": false,
    "size": "7.3 KiB",
    "date": "28-Sep-2025 13:24"
  },
  {
    "name": "goldnaxe.png",
    "href": "goldnaxe.png",
    "url": "https://myrient.erista.me/files/MAME/EXTRAs/all_non-zipped_content/snap_SL/ibm5150/goldnaxe.png",
    "is_dir": false,
    "size": "12.1 KiB",
    "date": "28-Sep-2025 13:24"
  },
  {
    "name": "gunboat.png",
    "href": "gunboat.png",
    "url": "https://myrient.erista.me/files/MAME/EXTRAs/all_non-zipped_content/snap_SL/ibm5150/gunboat.png",
    "is_dir": false,
    "size": "18.8 KiB",
    "date": "28-Sep-2025 13:24"
  },
  {
    "name": "homealon.png",
    "href": "homealon.png",
    "url": "https://myrient.erista.me/files/MAME/EXTRAs/all_non-zipped_content/snap_SL/ibm5150/homealon.png",
    "is_dir": false,
    "size": "14.5 KiB",
    "date": "28-Sep-2025 13:24"
  },
  {
    "name": "ikari.png",
    "href": "ikari.png",
    "url": "https://myrient.erista.me/files/MAME/EXTRAs/all_non-zipped_content/snap_SL/ibm5150/ikari.png",
    "is_dir": false,
    "size": "7.6 KiB",
    "date": "28-Sep-2025 13:24"
  },
  {
    "name": "indy500.png",
    "href": "indy500.png",
    "url": "https://myrient.erista.me/files/MAME/EXTRAs/all_non-zipped_content/snap_SL/ibm5150/indy500.png",
    "is_dir": false,
    "size": "31.1 KiB",
    "date": "28-Sep-2025 13:24"
  },
  {
    "name": "ironmnso.png",
    "href": "ironmnso.png",
    "url": "https://myrient.erista.me/files/MAME/EXTRAs/all_non-zipped_content/snap_SL/ibm5150/ironmnso.png",
    "is_dir": false,
    "size": "56.4 KiB",
    "date": "28-Sep-2025 13:24"
  },
  {
    "name": "jordbird.png",
    "href": "jordbird.png",
    "url": "https://myrient.erista.me/files/MAME/EXTRAs/all_non-zipped_content/snap_SL/ibm5150/jordbird.png",
    "is_dir": false,
    "size": "49.1 KiB",
    "date": "28-Sep-2025 13:24"
  },
  {
    "name": "jumpman.png",
    "href": "jumpman.png",
    "url": "https://myrient.erista.me/files/MAME/EXTRAs/all_non-zipped_content/snap_SL/ibm5150/jumpman.png",
    "is_dir": false,
    "size": "2.6 KiB",
    "date": "28-Sep-2025 13:24"
  },
  {
    "name": "kdreams.png",
    "href": "kdreams.png",
    "url": "https://myrient.erista.me/files/MAME/EXTRAs/all_non-zipped_content/snap_SL/ibm5150/kdreams.png",
    "is_dir": false,
    "size": "20.3 KiB",
    "date": "28-Sep-2025 13:24"
  },
  {
    "name": "keen123.png",
    "href": "keen123.png",
    "url": "https://myrient.erista.me/files/MAME/EXTRAs/all_non-zipped_content/snap_SL/ibm5150/keen123.png",
    "is_dir": false,
    "size": "6.0 KiB",
    "date": "28-Sep-2025 13:24"
  },
  {
    "name": "kingqst.png",
    "href": "kingqst.png",
    "url": "https://myrient.erista.me/files/MAME/EXTRAs/all_non-zipped_content/snap_SL/ibm5150/kingqst.png",
    "is_dir": false,
    "size": "5.2 KiB",
    "date": "28-Sep-2025 13:24"
  },
  {
    "name": "lakecelt.png",
    "href": "lakecelt.png",
    "url": "https://myrient.erista.me/files/MAME/EXTRAs/all_non-zipped_content/snap_SL/ibm5150/lakecelt.png",
    "is_dir": false,
    "size": "39.8 KiB",
    "date": "28-Sep-2025 13:24"
  },
  {
    "name": "ldrun.png",
    "href": "ldrun.png",
    "url": "https://myrient.erista.me/files/MAME/EXTRAs/all_non-zipped_content/snap_SL/ibm5150/ldrun.png",
    "is_dir": false,
    "size": "2.6 KiB",
    "date": "28-Sep-2025 13:24"
  },
  {
    "name": "lic2kill.png",
    "href": "lic2kill.png",
    "url": "https://myrient.erista.me/files/MAME/EXTRAs/all_non-zipped_content/snap_SL/ibm5150/lic2kill.png",
    "is_dir": false,
    "size": "33.3 KiB",
    "date": "28-Sep-2025 13:24"
  },
  {
    "name": "links.png",
    "href": "links.png",
    "url": "https://myrient.erista.me/files/MAME/EXTRAs/all_non-zipped_content/snap_SL/ibm5150/links.png",
    "is_dir": false,
    "size": "21.0 KiB",
    "date": "28-Sep-2025 13:24"
  },
  {
    "name": "linksbnt.png",
    "href": "linksbnt.png",
    "url": "https://myrient.erista.me/files/MAME/EXTRAs/all_non-zipped_content/snap_SL/ibm5150/linksbnt.png",
    "is_dir": false,
    "size": "28.7 KiB",
    "date": "28-Sep-2025 13:24"
  },
  {
    "name": "lockon.png",
    "href": "lockon.png",
    "url": "https://myrient.erista.me/files/MAME/EXTRAs/all_non-zipped_content/snap_SL/ibm5150/lockon.png",
    "is_dir": false,
    "size": "4.9 KiB",
    "date": "28-Sep-2025 13:24"
  },
  {
    "name": "mule.png",
    "href": "mule.png",
    "url": "https://myrient.erista.me/files/MAME/EXTRAs/all_non-zipped_content/snap_SL/ibm5150/mule.png",
    "is_dir": false,
    "size": "3.0 KiB",
    "date": "28-Sep-2025 13:24"
  },
  {
    "name": "nightmar.png",
    "href": "nightmar.png",
    "url": "https://myrient.erista.me/files/MAME/EXTRAs/all_non-zipped_content/snap_SL/ibm5150/nightmar.png",
    "is_dir": false,
    "size": "20.4 KiB",
    "date": "28-Sep-2025 13:24"
  },
  {
    "name": "npinbal.png",
    "href": "npinbal.png",
    "url": "https://myrient.erista.me/files/MAME/EXTRAs/all_non-zipped_content/snap_SL/ibm5150/npinbal.png",
    "is_dir": false,
    "size": "6.1 KiB",
    "date": "28-Sep-2025 13:24"
  },
  {
    "name": "opwolf.png",
    "href": "opwolf.png",
    "url": "https://myrient.erista.me/files/MAME/EXTRAs/all_non-zipped_content/snap_SL/ibm5150/opwolf.png",
    "is_dir": false,
    "size": "33.1 KiB",
    "date": "28-Sep-2025 13:24"
  },
  {
    "name": "outrun.png",
    "href": "outrun.png",
    "url": "https://myrient.erista.me/files/MAME/EXTRAs/all_non-zipped_content/snap_SL/ibm5150/outrun.png",
    "is_dir": false,
    "size": "14.2 KiB",
    "date": "28-Sep-2025 13:24"
  },
  {
    "name": "pcdos1.png",
    "href": "pcdos1.png",
    "url": "https://myrient.erista.me/files/MAME/EXTRAs/all_non-zipped_content/snap_SL/ibm5150/pcdos1.png",
    "is_dir": false,
    "size": "7.4 KiB",
    "date": "28-Sep-2025 13:24"
  },
  {
    "name": "pcdos11.png",
    "href": "pcdos11.png",
    "url": "https://myrient.erista.me/files/MAME/EXTRAs/all_non-zipped_content/snap_SL/ibm5150/pcdos11.png",
    "is_dir": false,
    "size": "8.5 KiB",
    "date": "28-Sep-2025 13:24"
  },
  {
    "name": "pcdos2.png",
    "href": "pcdos2.png",
    "url": "https://myrient.erista.me/files/MAME/EXTRAs/all_non-zipped_content/snap_SL/ibm5150/pcdos2.png",
    "is_dir": false,
    "size": "10.2 KiB",
    "date": "28-Sep-2025 13:24"
  },
  {
    "name": "pcdos21.png",
    "href": "pcdos21.png",
    "url": "https://myrient.erista.me/files/MAME/EXTRAs/all_non-zipped_content/snap_SL/ibm5150/pcdos21.png",
    "is_dir": false,
    "size": "7.8 KiB",
    "date": "28-Sep-2025 13:24"
  },
  {
    "name": "pcdos3.png",
    "href": "pcdos3.png",
    "url": "https://myrient.erista.me/files/MAME/EXTRAs/all_non-zipped_content/snap_SL/ibm5150/pcdos3.png",
    "is_dir": false,
    "size": "9.4 KiB",
    "date": "28-Sep-2025 13:24"
  },
  {
    "name": "pcdos31.png",
    "href": "pcdos31.png",
    "url": "https://myrient.erista.me/files/MAME/EXTRAs/all_non-zipped_content/snap_SL/ibm5150/pcdos31.png",
    "is_dir": false,
    "size": "9.7 KiB",
    "date": "28-Sep-2025 13:24"
  },
  {
    "name": "pcdos32.png",
    "href": "pcdos32.png",
    "url": "https://myrient.erista.me/files/MAME/EXTRAs/all_non-zipped_content/snap_SL/ibm5150/pcdos32.png",
    "is_dir": false,
    "size": "10.3 KiB",
    "date": "28-Sep-2025 13:24"
  },
  {
    "name": "pcdos33.png",
    "href": "pcdos33.png",
    "url": "https://myrient.erista.me/files/MAME/EXTRAs/all_non-zipped_content/snap_SL/ibm5150/pcdos33.png",
    "is_dir": false,
    "size": "8.8 KiB",
    "date": "28-Sep-2025 13:24"
  },
  {
    "name": "platoon.png",
    "href": "platoon.png",
    "url": "https://myrient.erista.me/files/MAME/EXTRAs/all_non-zipped_content/snap_SL/ibm5150/platoon.png",
    "is_dir": false,
    "size": "21.0 KiB",
    "date": "28-Sep-2025 13:24"
  },
  {
    "name": "ppersia.png",
    "href": "ppersia.png",
    "url": "https://myrient.erista.me/files/MAME/EXTRAs/all_non-zipped_content/snap_SL/ibm5150/ppersia.png",
    "is_dir": false,
    "size": "10.0 KiB",
    "date": "28-Sep-2025 13:24"
  },
  {
    "name": "prehist.png",
    "href": "prehist.png",
    "url": "https://myrient.erista.me/files/MAME/EXTRAs/all_non-zipped_content/snap_SL/ibm5150/prehist.png",
    "is_dir": false,
    "size": "39.4 KiB",
    "date": "28-Sep-2025 13:24"
  },
  {
    "name": "raster.png",
    "href": "raster.png",
    "url": "https://myrient.erista.me/files/MAME/EXTRAs/all_non-zipped_content/snap_SL/ibm5150/raster.png",
    "is_dir": false,
    "size": "4.6 KiB",
    "date": "28-Sep-2025 13:24"
  },
  {
    "name": "robocop.png",
    "href": "robocop.png",
    "url": "https://myrient.erista.me/files/MAME/EXTRAs/all_non-zipped_content/snap_SL/ibm5150/robocop.png",
    "is_dir": false,
    "size": "21.8 KiB",
    "date": "28-Sep-2025 13:24"
  },
  {
    "name": "satane.png",
    "href": "satane.png",
    "url": "https://myrient.erista.me/files/MAME/EXTRAs/all_non-zipped_content/snap_SL/ibm5150/satane.png",
    "is_dir": false,
    "size": "28.8 KiB",
    "date": "28-Sep-2025 13:24"
  },
  {
    "name": "sf.png",
    "href": "sf.png",
    "url": "https://myrient.erista.me/files/MAME/EXTRAs/all_non-zipped_content/snap_SL/ibm5150/sf.png",
    "is_dir": false,
    "size": "42.6 KiB",
    "date": "28-Sep-2025 13:24"
  },
  {
    "name": "shangon.png",
    "href": "shangon.png",
    "url": "https://myrient.erista.me/files/MAME/EXTRAs/all_non-zipped_content/snap_SL/ibm5150/shangon.png",
    "is_dir": false,
    "size": "10.0 KiB",
    "date": "28-Sep-2025 13:24"
  },
  {
    "name": "simcity.png",
    "href": "simcity.png",
    "url": "https://myrient.erista.me/files/MAME/EXTRAs/all_non-zipped_content/snap_SL/ibm5150/simcity.png",
    "is_dir": false,
    "size": "17.3 KiB",
    "date": "28-Sep-2025 13:24"
  },
  {
    "name": "simearth.png",
    "href": "simearth.png",
    "url": "https://myrient.erista.me/files/MAME/EXTRAs/all_non-zipped_content/snap_SL/ibm5150/simearth.png",
    "is_dir": false,
    "size": "23.8 KiB",
    "date": "28-Sep-2025 13:24"
  },
  {
    "name": "skatedie.png",
    "href": "skatedie.png",
    "url": "https://myrient.erista.me/files/MAME/EXTRAs/all_non-zipped_content/snap_SL/ibm5150/skatedie.png",
    "is_dir": false,
    "size": "8.8 KiB",
    "date": "28-Sep-2025 13:24"
  },
  {
    "name": "skweek.png",
    "href": "skweek.png",
    "url": "https://myrient.erista.me/files/MAME/EXTRAs/all_non-zipped_content/snap_SL/ibm5150/skweek.png",
    "is_dir": false,
    "size": "18.8 KiB",
    "date": "28-Sep-2025 13:24"
  },
  {
    "name": "spdball2.png",
    "href": "spdball2.png",
    "url": "https://myrient.erista.me/files/MAME/EXTRAs/all_non-zipped_content/snap_SL/ibm5150/spdball2.png",
    "is_dir": false,
    "size": "5.4 KiB",
    "date": "28-Sep-2025 13:24"
  },
  {
    "name": "stargoos.png",
    "href": "stargoos.png",
    "url": "https://myrient.erista.me/files/MAME/EXTRAs/all_non-zipped_content/snap_SL/ibm5150/stargoos.png",
    "is_dir": false,
    "size": "16.5 KiB",
    "date": "28-Sep-2025 13:24"
  },
  {
    "name": "storm.png",
    "href": "storm.png",
    "url": "https://myrient.erista.me/files/MAME/EXTRAs/all_non-zipped_content/snap_SL/ibm5150/storm.png",
    "is_dir": false,
    "size": "3.6 KiB",
    "date": "28-Sep-2025 13:24"
  },
  {
    "name": "superman.png",
    "href": "superman.png",
    "url": "https://myrient.erista.me/files/MAME/EXTRAs/all_non-zipped_content/snap_SL/ibm5150/superman.png",
    "is_dir": false,
    "size": "13.4 KiB",
    "date": "28-Sep-2025 13:24"
  },
  {
    "name": "term2.png",
    "href": "term2.png",
    "url": "https://myrient.erista.me/files/MAME/EXTRAs/all_non-zipped_content/snap_SL/ibm5150/term2.png",
    "is_dir": false,
    "size": "31.6 KiB",
    "date": "28-Sep-2025 13:24"
  },
  {
    "name": "tetris.png",
    "href": "tetris.png",
    "url": "https://myrient.erista.me/files/MAME/EXTRAs/all_non-zipped_content/snap_SL/ibm5150/tetris.png",
    "is_dir": false,
    "size": "19.1 KiB",
    "date": "28-Sep-2025 13:24"
  },
  {
    "name": "tmht2.png",
    "href": "tmht2.png",
    "url": "https://myrient.erista.me/files/MAME/EXTRAs/all_non-zipped_content/snap_SL/ibm5150/tmht2.png",
    "is_dir": false,
    "size": "25.9 KiB",
    "date": "28-Sep-2025 13:24"
  },
  {
    "name": "wizball.png",
    "href": "wizball.png",
    "url": "https://myrient.erista.me/files/MAME/EXTRAs/all_non-zipped_content/snap_SL/ibm5150/wizball.png",
    "is_dir": false,
    "size": "2.8 KiB",
    "date": "28-Sep-2025 13:24"
  },
  {
    "name": "wldgames.png",
    "href": "wldgames.png",
    "url": "https://myrient.erista.me/files/MAME/EXTRAs/all_non-zipped_content/snap_SL/ibm5150/wldgames.png",
    "is_dir": false,
    "size": "3.7 KiB",
    "date": "28-Sep-2025 13:24"
  },
  {
    "name": "wrathdem.png",
    "href": "wrathdem.png",
    "url": "https://myrient.erista.me/files/MAME/EXTRAs/all_non-zipped_content/snap_SL/ibm5150/wrathdem.png",
    "is_dir": false,
    "size": "20.5 KiB",
    "date": "28-Sep-2025 13:24"
  },
  {
    "name": "xenon.png",
    "href": "xenon.png",
    "url": "https://myrient.erista.me/files/MAME/EXTRAs/all_non-zipped_content/snap_SL/ibm5150/xenon.png",
    "is_dir": false,
    "size": "22.7 KiB",
    "date": "28-Sep-2025 13:24"
  },
  {
    "name": "zaxxon.png",
    "href": "zaxxon.png",
    "url": "https://myrient.erista.me/files/MAME/EXTRAs/all_non-zipped_content/snap_SL/ibm5150/zaxxon.png",
    "is_dir": false,
    "size": "3.7 KiB",
    "date": "28-Sep-2025 13:24"
  },
  {
    "name": "zool.png",
    "href": "zool.png",
    "url": "https://myrient.erista.me/files/MAME/EXTRAs/all_non-zipped_content/snap_SL/ibm5150/zool.png",
    "is_dir": false,
    "size": "3.4 KiB",
    "date": "28-Sep-2025 13:24"
  }
]