[
  {
    "name": "imd",
    "href": "imd/",
    "url": "https://myrient.erista.me/files/bitsavers/pdf/manx/imd/",
    "is_dir": true,
    "size": null,
    "date": "30-Sep-2008 21:19"
  },
  {
    "name": "Aztec_C86_User_Manual_Rel_1.05i_Jun83.pdf",
    "href": "Aztec_C86_User_Manual_Rel_1.05i_Jun83.pdf",
    "url": "https://myrient.erista.me/files/bitsavers/pdf/manx/Aztec_C86_User_Manual_Rel_1.05i_Jun83.pdf",
    "is_dir": false,
    "size": "3.2 MiB",
    "date": "26-Jan-2013 17:13"
  },
  {
    "name": "Aztec_C_1.05G_Rel_Note.pdf",
    "href": "Aztec_C_1.05G_Rel_Note.pdf",
    "url": "https://myrient.erista.me/files/bitsavers/pdf/manx/Aztec_C_1.05G_Rel_Note.pdf",
    "is_dir": false,
    "size": "318.8 KiB",
    "date": "30-Sep-2008 16:53"
  },
  {
    "name": "Aztec_C_1.05_User_Manual_Dec82.pdf",
    "href": "Aztec_C_1.05_User_Manual_Dec82.pdf",
    "url": "https://myrient.erista.me/files/bitsavers/pdf/manx/Aztec_C_1.05_User_Manual_Dec82.pdf",
    "is_dir": false,
    "size": "5.3 MiB",
    "date": "30-Sep-2008 21:10"
  },
  {
    "name": "Aztec_C_CPM_1.06D_Release_Notes.pdf",
    "href": "Aztec_C_CPM_1.06D_Release_Notes.pdf",
    "url": "https://myrient.erista.me/files/bitsavers/pdf/manx/Aztec_C_CPM_1.06D_Release_Notes.pdf",
    "is_dir": false,
    "size": "630.6 KiB",
    "date": "07-Apr-2013 17:51"
  },
  {
    "name": "Aztec_C_CPM_1.06_User_Manual_Mar84.pdf",
    "href": "Aztec_C_CPM_1.06_User_Manual_Mar84.pdf",
    "url": "https://myrient.erista.me/files/bitsavers/pdf/manx/Aztec_C_CPM_1.06_User_Manual_Mar84.pdf",
    "is_dir": false,
    "size": "8.4 MiB",
    "date": "07-Apr-2013 17:51"
  },
  {
    "name": "Aztec_C_Data_Sheet_Mar83.pdf",
    "href": "Aztec_C_Data_Sheet_Mar83.pdf",
    "url": "https://myrient.erista.me/files/bitsavers/pdf/manx/Aztec_C_Data_Sheet_Mar83.pdf",
    "is_dir": false,
    "size": "738.1 KiB",
    "date": "30-Sep-2008 16:53"
  },
  {
    "name": "Aztec_C_II_1.06b_Release_Document.pdf",
    "href": "Aztec_C_II_1.06b_Release_Document.pdf",
    "url": "https://myrient.erista.me/files/bitsavers/pdf/manx/Aztec_C_II_1.06b_Release_Document.pdf",
    "is_dir": false,
    "size": "205.1 KiB",
    "date": "11-Apr-2013 04:03"
  },
  {
    "name": "Aztec_C_II_Z80_User_Manual_1.05_Sep83.pdf",
    "href": "Aztec_C_II_Z80_User_Manual_1.05_Sep83.pdf",
    "url": "https://myrient.erista.me/files/bitsavers/pdf/manx/Aztec_C_II_Z80_User_Manual_1.05_Sep83.pdf",
    "is_dir": false,
    "size": "3.9 MiB",
    "date": "15-Nov-2012 17:37"
  },
  {
    "name": "Aztec_C_MSDOS_4.10C_Commercial_Apr88.pdf",
    "href": "Aztec_C_MSDOS_4.10C_Commercial_Apr88.pdf",
    "url": "https://myrient.erista.me/files/bitsavers/pdf/manx/Aztec_C_MSDOS_4.10C_Commercial_Apr88.pdf",
    "is_dir": false,
    "size": "24.5 MiB",
    "date": "19-Aug-2009 20:12"
  },
  {
    "name": "Aztec_C_MSDOS_4.10D_Commercial.zip",
    "href": "Aztec_C_MSDOS_4.10D_Commercial.zip",
    "url": "https://myrient.erista.me/files/bitsavers/pdf/manx/Aztec_C_MSDOS_4.10D_Commercial.zip",
    "is_dir": false,
    "size": "700.9 KiB",
    "date": "20-Aug-2009 03:18"
  },
  {
    "name": "Manx_C68K_ROM_3.6B_MSDOS.zip",
    "href": "Manx_C68K_ROM_3.6B_MSDOS.zip",
    "url": "https://myrient.erista.me/files/bitsavers/pdf/manx/Manx_C68K_ROM_3.6B_MSDOS.zip",
    "is_dir": false,
    "size": "188.7 KiB",
    "date": "20-Aug-2009 03:18"
  },
  {
    "name": "Manx_C68K_ROM_3.6B_MSDOS_Jun88.pdf",
    "href": "Manx_C68K_ROM_3.6B_MSDOS_Jun88.pdf",
    "url": "https://myrient.erista.me/files/bitsavers/pdf/manx/Manx_C68K_ROM_3.6B_MSDOS_Jun88.pdf",
    "is_dir": false,
    "size": "5.4 MiB",
    "date": "19-Aug-2009 20:15"
  }
]