[
  {
    "name": "arcade gears vol.1 - pu li ru la (japan).chd",
    "href": "arcade%20gears%20vol.1%20-%20pu%20li%20ru%20la%20%28japan%29.chd",
    "url": "https://myrient.erista.me/files/MAME/Software%20List%20CHDs%20%28merged%29/saturn/pulirula/arcade%20gears%20vol.1%20-%20pu%20li%20ru%20la%20%28japan%29.chd",
    "is_dir": false,
    "size": "226.0 MiB",
    "date": "28-Sep-2025 21:19"
  },
  {
    "name": "pulirula arcade gears (jpn) (dw0395).chd",
    "href": "pulirula%20arcade%20gears%20%28jpn%29%20%28dw0395%29.chd",
    "url": "https://myrient.erista.me/files/MAME/Software%20List%20CHDs%20%28merged%29/saturn/pulirula/pulirula%20arcade%20gears%20%28jpn%29%20%28dw0395%29.chd",
    "is_dir": false,
    "size": "226.0 MiB",
    "date": "29-Sep-2025 04:27"
  }
]